pandas_hug/__init__.py
pandas_hug/core.py
pandas_hug-0.14.0.dist-info/METADATA
pandas_hug-0.14.0.dist-info/WHEEL
pandas_hug-0.14.0.dist-info/licenses/LICENSE.txt
pandas_hug-0.14.0.dist-info/RECORD
