Metadata-Version: 2.1
Name: pandas-hug
Version: 0.14.0
Summary: a utility for space efficient dataframes
License-File: LICENSE.txt
Classifier: Intended Audience :: Developers
Classifier: License :: OSI Approved :: BSD License
Classifier: Operating System :: OS Independent
Classifier: Programming Language :: Python :: 3
Classifier: Programming Language :: Python :: 3 :: Only
Classifier: Topic :: Software Development
Requires-Python: >=3.7
Requires-Dist: pandas
